<?xml version='1.0' encoding='UTF-8' standalone='yes' ?><hierarchy rotation="0"><node index="0" text="" resource-id="" class="android.widget.FrameLayout" package="com.ganziman.shadowrun" content-desc="" checkable="false" checked="false" clickable="false" enabled="true" focusable="false" focused="false" scrollable="false" long-clickable="false" password="false" selected="false" bounds="[0,0][1080,2400]" drawing-order="0" hint=""><node index="0" text="" resource-id="" class="android.widget.LinearLayout" package="com.ganziman.shadowrun" content-desc="" checkable="false" checked="false" clickable="false" enabled="true" focusable="false" focused="false" scrollable="false" long-clickable="false" password="false" selected="false" bounds="[0,0][1080,2400]" drawing-order="1" hint=""><node index="0" text="" resource-id="android:id/content" class="android.widget.FrameLayout" package="com.ganziman.shadowrun" content-desc="" checkable="false" checked="false" clickable="false" enabled="true" focusable="false" focused="false" scrollable="false" long-clickable="false" password="false" selected="false" bounds="[0,0][1080,2400]" drawing-order="2" hint=""><node index="0" text="" resource-id="" class="android.widget.FrameLayout" package="com.ganziman.shadowrun" content-desc="" checkable="false" checked="false" clickable="false" enabled="true" focusable="true" focused="false" scrollable="false" long-clickable="false" password="false" selected="false" bounds="[0,0][1080,2400]" drawing-order="1" hint=""><node index="0" text="" resource-id="" class="android.view.View" package="com.ganziman.shadowrun" content-desc="" checkable="false" checked="false" clickable="false" enabled="true" focusable="false" focused="false" scrollable="false" long-clickable="false" password="false" selected="false" bounds="[0,0][1080,2400]" drawing-order="0" hint=""><node index="0" text="" resource-id="" class="android.view.View" package="com.ganziman.shadowrun" content-desc="" checkable="false" checked="false" clickable="false" enabled="true" focusable="false" focused="false" scrollable="false" long-clickable="false" password="false" selected="false" bounds="[0,0][1080,2400]" drawing-order="0" hint=""><node index="0" text="" resource-id="" class="android.view.View" package="com.ganziman.shadowrun" content-desc="" checkable="false" checked="false" clickable="false" enabled="true" focusable="false" focused="false" scrollable="false" long-clickable="false" password="false" selected="false" bounds="[0,0][1080,2400]" drawing-order="0" hint=""><node NAF="true" index="0" text="" resource-id="" class="android.widget.Button" package="com.ganziman.shadowrun" content-desc="" checkable="false" checked="false" clickable="true" enabled="true" focusable="true" focused="false" scrollable="false" long-clickable="false" password="false" selected="false" bounds="[11,84][137,210]" drawing-order="0" hint="" /><node index="1" text="" resource-id="" class="android.view.View" package="com.ganziman.shadowrun" content-desc="" checkable="false" checked="false" clickable="false" enabled="true" focusable="false" focused="false" scrollable="false" long-clickable="false" password="false" selected="false" bounds="[0,210][1080,2106]" drawing-order="0" hint=""><node index="0" text="" resource-id="" class="android.view.View" package="com.ganziman.shadowrun" content-desc="새 러닝" checkable="false" checked="false" clickable="false" enabled="true" focusable="true" focused="false" scrollable="false" long-clickable="false" password="false" selected="false" bounds="[412,633][668,761]" drawing-order="0" hint="" /><node index="1" text="" resource-id="" class="android.view.View" package="com.ganziman.shadowrun" content-desc="새로운 기록을 남겨라. 그림자가 지켜본다." checkable="false" checked="false" clickable="false" enabled="true" focusable="true" focused="false" scrollable="false" long-clickable="false" password="false" selected="false" bounds="[278,782][803,903]" drawing-order="0" hint="" /><node index="2" text="" resource-id="" class="android.view.View" package="com.ganziman.shadowrun" content-desc="러닝 모드 선택" checkable="false" checked="false" clickable="false" enabled="true" focusable="true" focused="false" scrollable="false" long-clickable="false" password="false" selected="false" bounds="[53,1032][337,1087]" drawing-order="0" hint="" /><node index="3" text="" resource-id="" class="android.view.View" package="com.ganziman.shadowrun" content-desc="전설의 마라토너&#10;코치와 함께 달리기" checkable="false" checked="false" clickable="true" enabled="true" focusable="true" focused="false" scrollable="false" long-clickable="false" password="false" selected="false" bounds="[53,1118][1028,1326]" drawing-order="0" hint="" /><node index="4" text="" resource-id="" class="android.view.View" package="com.ganziman.shadowrun" content-desc="자유 러닝&#10;자유롭게 기록만" checkable="false" checked="false" clickable="true" enabled="true" focusable="true" focused="false" scrollable="false" long-clickable="false" password="false" selected="false" bounds="[53,1347][1028,1551]" drawing-order="0" hint="" /><node index="5" text="" resource-id="" class="android.view.View" package="com.ganziman.shadowrun" content-desc="GPS 신호 양호" checkable="false" checked="false" clickable="false" enabled="true" focusable="true" focused="false" scrollable="false" long-clickable="false" password="false" selected="false" bounds="[448,1654][679,1701]" drawing-order="0" hint="" /></node><node index="2" text="" resource-id="" class="android.widget.Button" package="com.ganziman.shadowrun" content-desc="시작" checkable="false" checked="false" clickable="true" enabled="true" focusable="true" focused="false" scrollable="false" long-clickable="false" password="false" selected="false" bounds="[53,2106][1028,2253]" drawing-order="0" hint="" /></node></node></node></node></node></node></node></hierarchy>